INSTALL
LICENSE
MANIFEST.in
Makefile
README.md
attach.py
install.sh
setup.cpyext.py
setup.py
setup.pyuwsgi.py
uwsgi.h
uwsgi_main.c
uwsgiconfig.py
uwsgidecorators.py
apache2/mod_Ruwsgi.c
apache2/mod_proxy_uwsgi.c
apache2/mod_uwsgi.c
buildconf/all.ini
buildconf/asyncio.ini
buildconf/base.ini
buildconf/cgi.ini
buildconf/core.ini
buildconf/coroae.ini
buildconf/coverity.ini
buildconf/default.ini
buildconf/django.ini
buildconf/embedded.ini
buildconf/erlang.ini
buildconf/gccgo.ini
buildconf/gevent.ini
buildconf/glusterfs.ini
buildconf/gridfs.ini
buildconf/jwsgi.ini
buildconf/lib.ini
buildconf/lua.ini
buildconf/luap.ini
buildconf/minimal.ini
buildconf/modular.ini
buildconf/mono.ini
buildconf/nolang.ini
buildconf/package.ini
buildconf/php.ini
buildconf/plonly.ini
buildconf/ppa.ini
buildconf/psgi.ini
buildconf/pyerl.ini
buildconf/pylua.ini
buildconf/pyonly.ini
buildconf/pypy.ini
buildconf/pypyonly.ini
buildconf/pyring.ini
buildconf/pyuwsgi.ini
buildconf/pyuwsginossl.ini
buildconf/rack.ini
buildconf/rados.ini
buildconf/rbonly.ini
buildconf/ring.ini
buildconf/ruby2.ini
buildconf/servlet.ini
buildconf/travis.ini
buildconf/unbit.ini
buildconf/unbitstaff.ini
buildconf/uwsgi.it.ini
buildconf/v8.ini
core/alarm.c
core/alarm.o
core/async.c
core/async.o
core/buffer.c
core/buffer.o
core/cache.c
core/cache.o
core/chunked.c
core/chunked.o
core/clang_fake.c
core/clock.c
core/clock.o
core/config.c
core/config.o
core/config_py.c
core/config_py.o
core/cookie.c
core/cookie.o
core/cron.c
core/cron.o
core/daemons.c
core/daemons.o
core/dot_h.c
core/dot_h.o
core/emperor.c
core/emperor.o
core/errors.c
core/errors.o
core/event.c
core/event.o
core/exceptions.c
core/exceptions.o
core/fifo.c
core/fifo.o
core/fsmon.c
core/fsmon.o
core/gateway.c
core/gateway.o
core/hash.c
core/hash.o
core/hooks.c
core/hooks.o
core/ini.c
core/ini.o
core/init.c
core/init.o
core/io.c
core/io.o
core/json.c
core/legion.c
core/legion.o
core/lock.c
core/lock.o
core/logging.
core/logging.c
core/logging.o
core/loop.c
core/loop.o
nuwsgi.egg-info/PKG-INFO
nuwsgi.egg-info/SOURCES.txt
nuwsgi.egg-info/dependency_links.txt
nuwsgi.egg-info/top_level.txt
